monitoring/__init__.py
monitoring/admin.py
monitoring/apps.py
monitoring/models.py
monitoring/seeds.py
monitoring/serializers.py
monitoring/tests.py
monitoring/urls.py
monitoring/views.py
monitoring/migrations/0001_initial.py
monitoring/migrations/0002_source_meta_connector_source_meta_db_and_more.py
monitoring/migrations/0003_metric_contact_person_metric_type.py
monitoring/migrations/0004_alter_source_type.py
monitoring/migrations/__init__.py
monitoring/plugins/__init__.py
monitoring/plugins/sources/__init__.py
monitoring/plugins/sources/not_success_v1/__init__.py
monitoring/plugins/sources/not_success_v1/not_success_v1.py
monitoring/plugins/sources/sql_query_v1/__init__.py
monitoring/plugins/sources/sql_query_v1/sql_query_v1.py
monitoring/plugins/sources/sql_query_v2/__init__.py
monitoring/plugins/sources/sql_query_v2/sql_query_v2.py
monitoring/plugins/sources/sql_sage_gateway_v1/__init__.py
monitoring/plugins/sources/sql_sage_gateway_v1/sql_sage_gateway_v1.py
tests/__init__.py
tests/urls.py
shopcloud_django_monitoring-2.7.0.dist-info/LICENSE
shopcloud_django_monitoring-2.7.0.dist-info/METADATA
shopcloud_django_monitoring-2.7.0.dist-info/WHEEL
shopcloud_django_monitoring-2.7.0.dist-info/top_level.txt
shopcloud_django_monitoring-2.7.0.dist-info/RECORD
