Metadata-Version: 2.1
Name: shopcloud-django-monitoring
Version: 2.7.0
Summary: A Module for create site reliable engineering
Home-page: https://github.com/Talk-Point/shopcloud-django-monitoring
Author: Konstantin Stoldt
Author-email: konstantin.stoldt@talk-point.de
License: MIT
License-File: LICENSE
Requires-Dist: Django <6.0,>=3.2
Requires-Dist: shopcloud-streams
Requires-Dist: shopcloud-django-toolbox
Requires-Dist: shopcloud-django-instrumenting
Requires-Dist: djangorestframework
Requires-Dist: django-filter
Requires-Dist: markdown
